ccontext_mcp/__init__.py
ccontext_mcp/schema.py
ccontext_mcp/server.py
ccontext_mcp/storage.py
ccontext_mcp/tools.py
ccontext_mcp-0.1.12.dist-info/METADATA
ccontext_mcp-0.1.12.dist-info/WHEEL
ccontext_mcp-0.1.12.dist-info/entry_points.txt
ccontext_mcp-0.1.12.dist-info/RECORD
